baseutils_phornee/__init__.py
baseutils_phornee/config.py
baseutils_phornee/logger.py
baseutils_phornee/utils.py
tests/__init__.py
tests/test_config.py
tests/data/__init__.py
tests/data/config_existing.yml
tests/data/config_template.yml
baseutils_phornee-0.1.2.dist-info/METADATA
baseutils_phornee-0.1.2.dist-info/WHEEL
baseutils_phornee-0.1.2.dist-info/top_level.txt
baseutils_phornee-0.1.2.dist-info/RECORD
