Metadata-Version: 2.1
Name: baseutils-phornee
Version: 0.1.2
Summary: Utility modules for Class management
Home-page: https://github.com/Phornee/baseutils_phornee
Author: Ismael Raya
Author-email: phornee@gmail.com
License: UNKNOWN
Platform: UNKNOWN
Classifier: Programming Language :: Python :: 3
Classifier: License :: OSI Approved :: MIT License
Classifier: Operating System :: OS Independent
Requires-Python: >=3.6
Requires-Dist: PyYAML (>=5.3.1)
